pynsgr/__init__.py
pynsgr/client.py
pynsgr/pyjavaproperties.py
pynsgr/commands/__init__.py
pynsgr/commands/nsgr_job.py
pynsgr/commands/nsgr_submit.py
pynsgr-1.0.3.dist-info/LICENSE
pynsgr-1.0.3.dist-info/METADATA
pynsgr-1.0.3.dist-info/WHEEL
pynsgr-1.0.3.dist-info/entry_points.txt
pynsgr-1.0.3.dist-info/top_level.txt
pynsgr-1.0.3.dist-info/RECORD
