Metadata-Version: 2.1
Name: pynsgr
Version: 1.0.3
Home-page: https://github.com/OpenSourceBrain/pynsgr
Author: "Terry Schwartz, Padraig Gleeson"
Author-email: terri@sdsc.edu
License: MIT
Classifier: Intended Audience :: Science/Research
Classifier: License :: OSI Approved :: MIT License
Classifier: Natural Language :: English
Classifier: Operating System :: OS Independent
Classifier: Programming Language :: Python :: 3.7
Classifier: Programming Language :: Python :: 3.8
Classifier: Programming Language :: Python :: 3.9
Classifier: Programming Language :: Python :: 3.10
Classifier: Programming Language :: Python :: 3.11
Classifier: Topic :: Scientific/Engineering
License-File: LICENSE
Requires-Dist: requests (>=2.5.3)
